{
  "repos": [
  {
    "url": "Achuan-2/siyuan-themes-tsundoku-light@4a38aa8225375eaec9e8f57b2e9ec4bf3d694993",
    "updated": "2022-06-09T05:42:51Z",
    "stars": 53,
    "openIssues": 0,
    "size": 9642353
  },
  {
    "url": "Achuan-2/siyuan-themes-tsundoku-stone@aae0b5635edb36475e1aff3edc4dc2880572ed7d",
    "updated": "2022-06-09T05:42:51Z",
    "stars": 8,
    "openIssues": 0,
    "size": 12866895
  },
  {
    "url": "Achuan-2/siyuan-themes-tsundoku-green@793954526647dad77c8eda9b59ab9a457fd263a2",
    "updated": "2022-06-09T05:42:50Z",
    "stars": 15,
    "openIssues": 0,
    "size": 12956460
  },
  {
    "url": "Achuan-2/siyuan-themes-tsundoku-dark@01b7851cee77ecf334dc36f6c762551e07defca9",
    "updated": "2022-06-09T05:42:49Z",
    "stars": 47,
    "openIssues": 3,
    "size": 9843806
  },
  {
    "url": "mindstudy/siyuan-themes-concise-dark@ed2883044467e14946d70d62c96e2ffe6a6edbb7",
    "updated": "2022-06-09T02:51:14Z",
    "stars": 4,
    "openIssues": 0,
    "size": 1143950
  },
  {
    "url": "mindstudy/siyuan-themes-concise-light@8b02cdc7b158b121ae50fd3b3430cc58faf39543",
    "updated": "2022-06-09T02:50:40Z",
    "stars": 5,
    "openIssues": 0,
    "size": 1196231
  },
  {
    "url": "lisontowind/purelight@cd50e84b25daa002f18bd51ced3a33610a503348",
    "updated": "2022-06-08T07:58:51Z",
    "stars": 2,
    "openIssues": 0,
    "size": 5734993
  },
  {
    "url": "lisontowind/puredark@ca80430d93868479b97bb585071047975a71a8e9",
    "updated": "2022-06-08T07:57:04Z",
    "stars": 1,
    "openIssues": 0,
    "size": 5758029
  },
  {
    "url": "Morganwan90/Lightblue-siyuan-theme@50d210303a2b0b372f0e2bb945bd06d971fef675",
    "updated": "2022-06-07T17:01:17Z",
    "stars": 21,
    "openIssues": 0,
    "size": 6127091
  },
  {
    "url": "Morganwan90/Darkblue-siyuan-theme@c5c8ba225ff575b01d092b9cc443a0a94137d88a",
    "updated": "2022-06-07T17:00:54Z",
    "stars": 18,
    "openIssues": 0,
    "size": 6118426
  },
  {
    "url": "royc01/notion-theme@d269a4a5a57add6a0f9eaaea5213d573cb8ac3f5",
    "updated": "2022-06-07T14:27:08Z",
    "stars": 24,
    "openIssues": 1,
    "size": 1271575
  },
  {
    "url": "royc01/notion-dark@9145b7781202b93609a37dd0115d3c97ec848483",
    "updated": "2022-06-07T14:26:55Z",
    "stars": 18,
    "openIssues": 0,
    "size": 1288546
  },
  {
    "url": "royc01/salt@df29842607d298343750e519a225dd2b3a076f91",
    "updated": "2022-06-07T14:26:44Z",
    "stars": 2,
    "openIssues": 1,
    "size": 1152061
  },
  {
    "url": "Zuoqiu-Yingyi/siyuan-theme-dark-plus@4c0a2035b1584595eddd3a45cdb2950f598855cf",
    "updated": "2022-06-06T12:09:59Z",
    "stars": 56,
    "openIssues": 17,
    "size": 17530184
  },
  {
    "url": "UFDXD/HBuilderX-Light@1af3cd7854a5a2b63f72255aa9380ef237aa61ce",
    "updated": "2022-06-02T13:18:26Z",
    "stars": 1,
    "openIssues": 0,
    "size": 3373143
  },
  {
    "url": "luckept/vert@cd2a7121512af1f6c4e9da1b08029eaf371ea25d",
    "updated": "2022-06-02T12:48:14Z",
    "stars": 11,
    "openIssues": 7,
    "size": 2157903
  },
  {
    "url": "UserZYF/blue-dog@e2eced978649c1e6045b841221bd4082946c03db",
    "updated": "2022-05-29T09:56:56Z",
    "stars": 5,
    "openIssues": 0,
    "size": 572807
  },
  {
    "url": "weihan-Chen/CityInDark@456aacfb96ee49eb8f1786d6c19543a4836e8443",
    "updated": "2022-05-25T12:40:33Z",
    "stars": 2,
    "openIssues": 1,
    "size": 4431300
  },
  {
    "url": "UserZYF/zhang-dark@e7328c962af718de448864a42abe2baa37587e2d",
    "updated": "2022-05-25T10:53:26Z",
    "stars": 4,
    "openIssues": 0,
    "size": 835606
  },
  {
    "url": "UserZYF/zhang-light@5073e0caeebb4dd0e46186f715e7732dbb2c2284",
    "updated": "2022-05-25T10:49:02Z",
    "stars": 41,
    "openIssues": 13,
    "size": 931541
  },
  {
    "url": "UserZYF/min-verse@a55ee6c891169262d702f60d9517643cc69c748b",
    "updated": "2022-05-24T12:25:57Z",
    "stars": 0,
    "openIssues": 1,
    "size": 7226625
  },
  {
    "url": "UserZYF/green-elephant@c31e20f3b9095fec0a800d5f5de8e57ae2c46e52",
    "updated": "2022-05-24T12:23:57Z",
    "stars": 0,
    "openIssues": 2,
    "size": 290612
  },
  {
    "url": "UserZYF/chuizi@9e59ccfcd781af8ed26882f1f45667bf114ab6c0",
    "updated": "2022-05-24T12:21:35Z",
    "stars": 0,
    "openIssues": 0,
    "size": 1156759
  },
  {
    "url": "UserZYF/Chrome-A4@17dcf2fa3b837517165d01ca8224299a0fe05d59",
    "updated": "2022-05-24T12:16:06Z",
    "stars": 9,
    "openIssues": 0,
    "size": 180619
  },
  {
    "url": "lanedu/Knowledge-Brain@9189bddb107c0bbf9be09ad724f2abb282de9ff9",
    "updated": "2022-05-22T07:37:53Z",
    "stars": 20,
    "openIssues": 9,
    "size": 19587589
  },
  {
    "url": "idea-zone/mini-vlook@732a714046c9c8a529946cd5643b4835bbbcb8c8",
    "updated": "2022-05-20T10:34:02Z",
    "stars": 3,
    "openIssues": 1,
    "size": 4548831
  },
  {
    "url": "YYHCOPPOLO/BluePrint-From-Tsundoku@ffd0bda5cf9fe3fa4b5f6a1e1c981a077910df3e",
    "updated": "2022-05-16T13:57:31Z",
    "stars": 2,
    "openIssues": 0,
    "size": 9400114
  },
  {
    "url": "zqhjl/Rem-Craft@21f89b7deddbf0a78d5d2b6bdd1b59358dfc6204",
    "updated": "2022-04-16T14:03:29Z",
    "stars": 39,
    "openIssues": 6,
    "size": 7289404
  },
  {
    "url": "wxf-0415/gentle-blue@520b3149e3a851223124cd814dba5d60063eeeaf",
    "updated": "2022-03-20T06:32:44Z",
    "stars": 2,
    "openIssues": 2,
    "size": 2160694
  },
  {
    "url": "thiqee/paperX@748564fdc09b8cb65c146207dc1d824b3561d58b",
    "updated": "2022-02-17T09:49:46Z",
    "stars": 2,
    "openIssues": 0,
    "size": 12367951
  },
  {
    "url": "Crowds21/Cliff-Dark@47d8102feef71cee35f960e8628694eeb6c3cff2",
    "updated": "2022-02-17T04:31:18Z",
    "stars": 2,
    "openIssues": 0,
    "size": 5168167
  },
  {
    "url": "geekmai/BearLight_for_SiYuan@0f90e7629498ec5a86c459f153480db9af4f9d38",
    "updated": "2022-01-19T14:01:38Z",
    "stars": 9,
    "openIssues": 2,
    "size": 382885
  }
]
}